{
  "actions": [
    {
      "name": "startATaskToCalculateViolationsForAnAccessRequest",
      "protocol": "REST",
      "method": "POST",
      "entitypath": "{base_path}/{version}/securetrack/api/violations/access_requests/task?{query}",
      "requestSchema": "schema.json",
      "responseSchema": "schema.json",
      "timeout": 0,
      "sendEmpty": false,
      "sendGetBody": false,
      "requestDatatype": "JSON",
      "responseDatatype": "JSON",
      "headers": {},
      "responseObjects": [
        {
          "type": "default",
          "key": "",
          "mockFile": ""
        }
      ]
    },
    {
      "name": "getViolationTaskResults",
      "protocol": "REST",
      "method": "GET",
      "entitypath": "{base_path}/{version}/securetrack/api/violations/access_requests/result/{pathv1}?{query}",
      "requestSchema": "schema.json",
      "responseSchema": "schema.json",
      "timeout": 0,
      "sendEmpty": false,
      "sendGetBody": false,
      "requestDatatype": "JSON",
      "responseDatatype": "JSON",
      "headers": {},
      "responseObjects": [
        {
          "type": "default",
          "key": "",
          "mockFile": ""
        }
      ]
    },
    {
      "name": "getViolationTaskStatus",
      "protocol": "REST",
      "method": "GET",
      "entitypath": "{base_path}/{version}/securetrack/api/violations/access_requests/status/{pathv1}?{query}",
      "requestSchema": "schema.json",
      "responseSchema": "schema.json",
      "timeout": 0,
      "sendEmpty": false,
      "sendGetBody": false,
      "requestDatatype": "JSON",
      "responseDatatype": "JSON",
      "headers": {},
      "responseObjects": [
        {
          "type": "default",
          "key": "",
          "mockFile": ""
        }
      ]
    },
    {
      "name": "cancelViolationTask",
      "protocol": "REST",
      "method": "DELETE",
      "entitypath": "{base_path}/{version}/securetrack/api/violations/access_requests/task/{pathv1}?{query}",
      "requestSchema": "schema.json",
      "responseSchema": "schema.json",
      "timeout": 0,
      "sendEmpty": false,
      "sendGetBody": false,
      "requestDatatype": "JSON",
      "responseDatatype": "JSON",
      "headers": {},
      "responseObjects": [
        {
          "type": "default",
          "key": "",
          "mockFile": ""
        }
      ]
    },
    {
      "name": "getViolationsForAnAccessRequest",
      "protocol": "REST",
      "method": "POST",
      "entitypath": "{base_path}/{version}/securetrack/api/violations/access_requests/sync?{query}",
      "requestSchema": "schema.json",
      "responseSchema": "schema.json",
      "timeout": 0,
      "sendEmpty": false,
      "sendGetBody": false,
      "requestDatatype": "JSON",
      "responseDatatype": "JSON",
      "headers": {},
      "responseObjects": [
        {
          "type": "default",
          "key": "",
          "mockFile": ""
        }
      ]
    }
  ]
}